dxt/prepare-DXT.py
mcp_simple_timeserver/__init__.py
mcp_simple_timeserver/__main__.py
mcp_simple_timeserver/core.py
mcp_simple_timeserver/server.py
mcp_simple_timeserver-3.3.0.dist-info/licenses/LICENSE
mcp_simple_timeserver-3.3.0.dist-info/METADATA
mcp_simple_timeserver-3.3.0.dist-info/WHEEL
mcp_simple_timeserver-3.3.0.dist-info/entry_points.txt
mcp_simple_timeserver-3.3.0.dist-info/top_level.txt
mcp_simple_timeserver-3.3.0.dist-info/RECORD
