Metadata-Version: 2.4
Name: mcp-simple-timeserver
Version: 3.3.0
Summary: A simple MCP server that provides current time - either local or from an NTP server.
Author-email: Andy Brandt <andy@codesprinters.com>
Project-URL: Homepage, https://github.com/andybrandt/mcp-simple-timeserver
Classifier: Programming Language :: Python :: 3
Classifier: License :: OSI Approved :: MIT License
Classifier: Operating System :: OS Independent
Requires-Python: >=3.11
License-File: LICENSE
Requires-Dist: fastmcp<3.0,>=2.14
Requires-Dist: ntplib
Requires-Dist: hijridate
Requires-Dist: japanera
Requires-Dist: pyluach
Requires-Dist: persiantools
Requires-Dist: pywin32; sys_platform == "win32"
Requires-Dist: timezonefinder>=6.0
Requires-Dist: requests>=2.28
Requires-Dist: tzdata
Requires-Dist: pycountry>=24.0
Provides-Extra: cli
Requires-Dist: fastmcp[cli]; extra == "cli"
Dynamic: license-file
